<annotation>
	<folder>dick</folder>
	<filename>101.brian-j-white-nude-689x1024 (3rd copy).jpg</filename>
	<path>/home/ghost/Desktop/object_detection_demo/data/images/dick/101.brian-j-white-nude-689x1024 (3rd copy).jpg</path>
	<source>
		<database>Unknown</database>
	</source>
	<size>
		<width>181</width>
		<height>186</height>
		<depth>3</depth>
	</size>
	<segmented>0</segmented>
	<object>
		<name>penis</name>
		<pose>Unspecified</pose>
		<truncated>0</truncated>
		<difficult>0</difficult>
		<bndbox>
			<xmin>91</xmin>
			<ymin>58</ymin>
			<xmax>171</xmax>
			<ymax>134</ymax>
		</bndbox>
	</object>
</annotation>
