<annotation>
	<folder>vagina</folder>
	<filename>8.preview.jpg</filename>
	<path>/home/ghost/Desktop/object_detection_demo/data/images/vagina/8.preview.jpg</path>
	<source>
		<database>Unknown</database>
	</source>
	<size>
		<width>233</width>
		<height>232</height>
		<depth>3</depth>
	</size>
	<segmented>0</segmented>
	<object>
		<name>vagina</name>
		<pose>Unspecified</pose>
		<truncated>0</truncated>
		<difficult>0</difficult>
		<bndbox>
			<xmin>78</xmin>
			<ymin>69</ymin>
			<xmax>157</xmax>
			<ymax>166</ymax>
		</bndbox>
	</object>
</annotation>
